LICENSE
MANIFEST.in
README.rst
setup.py
django_pde.egg-info/PKG-INFO
django_pde.egg-info/SOURCES.txt
django_pde.egg-info/dependency_links.txt
django_pde.egg-info/not-zip-safe
django_pde.egg-info/requires.txt
django_pde.egg-info/top_level.txt
pde/__init__.py
pde/admin.py
pde/apps.py
pde/models.py
pde/tests.py
pde/urls.py
pde/views.py
pde/management/__init__.py
pde/management/commands/__init__.py
pde/management/commands/_private.py
pde/management/commands/_pyckstart.py
pde/management/commands/pde.py
pde/management/commands/startpackage.py
pde/templates/pde/LICENCE.txt.tpl
pde/templates/pde/MANIFEST.in.tpl
pde/templates/pde/README.rst.tpl
pde/templates/pde/__init__.py.tpl
pde/templates/pde/package_name.py.tpl
pde/templates/pde/setup.py.tpl
pde/templates/pde/bin/__init__.py.tpl
pde/templates/pde/bin/main.py.tpl
pde/templates/pde/git/gitignore.tpl
pde/templates/pde/tests/__init__.py.tpl
pde/templates/pde/tests/test_package_name.py.tpl