Metadata-Version: 1.1
Name: django-pde
Version: 0.5.0
Summary: Django app that can be used to easily manage development of other django packages
Home-page: https://github.com/danleyb2/django-pde/wiki
Author: danleyb2<ndieksman@gmail.com>
Author-email: ndieksman@gmail.com
License: GNU License
Platform: UNKNOWN
Classifier: Environment :: Console
Classifier: Framework :: Django :: 1.9
Classifier: Intended Audience :: Developers
Classifier: License :: OSI Approved :: GNU General Public License v3 (GPLv3)
Classifier: Operating System :: POSIX :: Linux
Classifier: Programming Language :: Python
Classifier: Programming Language :: Python :: 2.7
Classifier: Programming Language :: Python :: 3
Classifier: Programming Language :: Python :: 3.2
Classifier: Programming Language :: Python :: 3.4
Classifier: Topic :: Utilities
Classifier: Topic :: Internet :: WWW/HTTP
